Workbook

Sheet Fundraising
B2: 2026 WA Supreme Court — PDC Fundraising Totals
B3: Ground truth as of 2026-05-19 · Source: web.pdc.wa.gov · 16 candidates across 5 ballot seats
B5: Pos | C5: Candidate | D5: Status | E5: Lean on ESSB 6346 / Culliton | F5: Lean Confidence | G5: Raised | H5: Spent | I5: Cash on Hand | J5: As of | K5: PDC Committee URL
B6: 1 | C6: Colleen Melody | D6: Incumbent | E6: Scrap (clears way for income tax) | F6: Medium | G6: 168517.6 | H6: 61257.92 | I6: =G6-H6 -> 107259.68 | J6: 2026-05-07 | K6: https://www.pdc.wa.gov/political-disclosure-reporting-data/browse-search-data/candidates/3391023
B7: 1 | C7: Scott Edwards | E7: Keep (defeats income tax) | F7: Medium-High | G7: 11124.34 | H7: 719.84 | I7: =G7-H7 -> 10404.5 | J7: 2026-05-11 | K7: https://www.pdc.wa.gov/political-disclosure-reporting-data/browse-search-data/candidates/3391385
B8: 1 | C8: Laura Christensen Colberg | E8: Unclear | F8: Low | G8: Not filed | H8: — | I8: — | J8: — | K8: https://www.pdc.wa.gov/political-disclosure-reporting-data/browse-search-data/candidates/3393509
B9: 3 | C9: J. Michael Diaz | D9: Front-runner | E9: Scrap (clears way for income tax) | F9: Medium | G9: 135435.75 | H9: 27557.58 | I9: =G9-H9 -> 107878.17 | J9: 2026-04-30 | K9: https://www.pdc.wa.gov/political-disclosure-reporting-data/browse-search-data/candidates/3391093
B10: 3 | C10: Jaime Hawk | E10: Scrap (clears way for income tax) | F10: Medium | G10: 102249.56 | H10: 5117.1 | I10: =G10-H10 -> 97132.46 | J10: 2026-05-11 | K10: https://www.pdc.wa.gov/political-disclosure-reporting-data/browse-search-data/candidates/3391607
B11: 3 | C11: David Stevens | E11: Keep (defeats income tax) | F11: Medium-High | G11: 12080.11 | H11: 2507.3 | I11: =G11-H11 -> 9572.81 | J11: 2026-05-11 | K11: https://www.pdc.wa.gov/political-disclosure-reporting-data/browse-search-data/candidates/3391236
B12: 4 | C12: Ian Birk | D12: Front-runner | E12: Scrap (clears way for income tax) | F12: Medium | G12: 269765 | H12: 39687.58 | I12: =G12-H12 -> 230077.42 | J12: 2026-05-11 | K12: https://www.pdc.wa.gov/political-disclosure-reporting-data/browse-search-data/candidates/3391099
B13: 4 | C13: Sean O'Donnell | E13: Unclear | F13: Low | G13: 167322.04 | H13: 25679.01 | I13: =G13-H13 -> 141643.03 | J13: 2026-05-11 | K13: https://www.pdc.wa.gov/political-disclosure-reporting-data/browse-search-data/candidates/3390933
B14: 5 | C14: Theo Angelis | D14: Incumbent | E14: Scrap (clears way for income tax) | F14: Medium | G14: 143610.71 | H14: 19043.78 | I14: =G14-H14 -> 124566.93 | J14: 2026-05-12 | K14: https://www.pdc.wa.gov/political-disclosure-reporting-data/browse-search-data/candidates/3391361
B15: 5 | C15: David Larson | E15: Keep (defeats income tax) | F15: High | G15: 138823.42 | H15: 30455.07 | I15: =G15-H15 -> 108368.35 | J15: 2026-05-11 | K15: https://www.pdc.wa.gov/political-disclosure-reporting-data/browse-search-data/candidates/3391234
B16: 5 | C16: Sharonda Amamilo | E16: Unclear | F16: Low | G16: 15181.31 | H16: 960.11 | I16: =G16-H16 -> 14221.2 | J16: 2026-05-18 | K16: https://www.pdc.wa.gov/political-disclosure-reporting-data/browse-search-data/candidates/3391132
B17: 5 | C17: Greg Miller | E17: Unclear | F17: Low | G17: Not filed | H17: 0 | I17: — | J17: 2026-05-14 | K17: https://www.pdc.wa.gov/political-disclosure-reporting-data/browse-search-data/candidates/3394415
B18: 7 | C18: Debra Stephens | D18: Incumbent | E18: Keep (defeats income tax) | F18: High | G18: 26513.38 | H18: 1500 | I18: =G18-H18 -> 25013.38 | J18: 2026-04-30 | K18: https://www.pdc.wa.gov/political-disclosure-reporting-data/browse-search-data/candidates/93052
B19: 7 | C19: David Shelvey | E19: Unclear | F19: Low | G19: Not filed | H19: — | I19: — | J19: — | K19: https://www.pdc.wa.gov/political-disclosure-reporting-data/browse-search-data/candidates/3377725
B20: 7 | C20: Karim Merchant | E20: Unclear | F20: Low | G20: Not filed | H20: — | I20: — | J20: — | K20: https://www.pdc.wa.gov/political-disclosure-reporting-data/browse-search-data/candidates/3395477
B21: 7 | C21: Todd Bloom | E21: Keep (defeats income tax) | F21: High | G21: Not filed | H21: — | I21: — | J21: 2026-05-08 | K21: https://www.pdc.wa.gov/political-disclosure-reporting-data/browse-search-data/candidates/3395177
C23: TOTAL (filed only) | G23: =SUM(G6:G21) -> 1190623.2 | H23: =SUM(H6:H21) -> 214485.29 | I23: =SUM(I6:I21) -> 976137.93

Sheet Summary by Lean
B2: Money by Likely Ruling on Culliton / ESSB 6346
B3: How candidate fundraising splits by likely vote on the income-tax precedent
B5: Group | C5: # Candidates | D5: Total Raised | E5: Total Cash on Hand | F5: Avg Raised
B6: Scrap (clears way for income tax) | C6: =COUNTIF(Fundraising!E6:E21,"Scrap*") -> 5 | D6: =SUMIFS(Fundraising!G6:G21,Fundraising!E6:E21,"Scrap*") -> 819578.62 | E6: =SUMIFS(Fundraising!I6:I21,Fundraising!E6:E21,"Scrap*") -> 666914.66 | F6: =IFERROR(D6/COUNTIFS(Fundraising!E6:E21,"Scrap*",Fundraising!G6:G21,">0"),"—") -> 163915.72
B7: Keep (defeats income tax) | C7: =COUNTIF(Fundraising!E6:E21,"Keep*") -> 5 | D7: =SUMIFS(Fundraising!G6:G21,Fundraising!E6:E21,"Keep*") -> 188541.25 | E7: =SUMIFS(Fundraising!I6:I21,Fundraising!E6:E21,"Keep*") -> 153359.04 | F7: =IFERROR(D7/COUNTIFS(Fundraising!E6:E21,"Keep*",Fundraising!G6:G21,">0"),"—") -> 47135.312
B8: Unclear | C8: =COUNTIF(Fundraising!E6:E21,"Unclear*") -> 6 | D8: =SUMIFS(Fundraising!G6:G21,Fundraising!E6:E21,"Unclear*") -> 182503.35 | E8: =SUMIFS(Fundraising!I6:I21,Fundraising!E6:E21,"Unclear*") -> 155864.23 | F8: =IFERROR(D8/COUNTIFS(Fundraising!E6:E21,"Unclear*",Fundraising!G6:G21,">0"),"—") -> 91251.675
B10: TOTAL (all candidates) | C10: =COUNTA(Fundraising!C6:C21) -> 16 | D10: =SUM(Fundraising!G6:G21) -> 1190623.2 | E10: =SUM(Fundraising!I6:I21) -> 976137.93 | F10: =IFERROR(D10/COUNTIF(Fundraising!G6:G21,">0"),"—") -> 108238.47
B13: By Ballot Seat
B14: Position | C14: # Candidates | D14: Total Raised | E14: Total Cash on Hand | F14: Leading Candidate by COH
B15: Position 1 | C15: =COUNTIF(Fundraising!B6:B21,1) -> 3 | D15: =SUMIFS(Fundraising!G6:G21,Fundraising!B6:B21,1) -> 179641.94 | E15: =SUMIFS(Fundraising!I6:I21,Fundraising!B6:B21,1) -> 117664.18 | F15: =IFERROR(INDEX(Fundraising!C6:C21,MATCH(maxifs(Fundraising!I6:I21,Fundraising!B6:B21,1),IF(Fundraising!B6:B21=1,Fundraising!I6:I21),0)),"—") -> —
B16: Position 3 | C16: =COUNTIF(Fundraising!B6:B21,3) -> 3 | D16: =SUMIFS(Fundraising!G6:G21,Fundraising!B6:B21,3) -> 249765.42 | E16: =SUMIFS(Fundraising!I6:I21,Fundraising!B6:B21,3) -> 214583.44 | F16: =IFERROR(INDEX(Fundraising!C6:C21,MATCH(maxifs(Fundraising!I6:I21,Fundraising!B6:B21,3),IF(Fundraising!B6:B21=3,Fundraising!I6:I21),0)),"—") -> —
B17: Position 4 | C17: =COUNTIF(Fundraising!B6:B21,4) -> 2 | D17: =SUMIFS(Fundraising!G6:G21,Fundraising!B6:B21,4) -> 437087.04 | E17: =SUMIFS(Fundraising!I6:I21,Fundraising!B6:B21,4) -> 371720.45 | F17: =IFERROR(INDEX(Fundraising!C6:C21,MATCH(maxifs(Fundraising!I6:I21,Fundraising!B6:B21,4),IF(Fundraising!B6:B21=4,Fundraising!I6:I21),0)),"—") -> —
B18: Position 5 | C18: =COUNTIF(Fundraising!B6:B21,5) -> 4 | D18: =SUMIFS(Fundraising!G6:G21,Fundraising!B6:B21,5) -> 297615.44 | E18: =SUMIFS(Fundraising!I6:I21,Fundraising!B6:B21,5) -> 247156.48 | F18: =IFERROR(INDEX(Fundraising!C6:C21,MATCH(maxifs(Fundraising!I6:I21,Fundraising!B6:B21,5),IF(Fundraising!B6:B21=5,Fundraising!I6:I21),0)),"—") -> —
B19: Position 7 | C19: =COUNTIF(Fundraising!B6:B21,7) -> 4 | D19: =SUMIFS(Fundraising!G6:G21,Fundraising!B6:B21,7) -> 26513.38 | E19: =SUMIFS(Fundraising!I6:I21,Fundraising!B6:B21,7) -> 25013.38 | F19: =IFERROR(INDEX(Fundraising!C6:C21,MATCH(maxifs(Fundraising!I6:I21,Fundraising!B6:B21,7),IF(Fundraising!B6:B21=7,Fundraising!I6:I21),0)),"—") -> —

Sheet Notes & Methodology
B2: Notes & Methodology
B4: Snapshot date
B5: 2026-05-19
B6: Election cycle
B7: 2026 — 5 of 9 Washington State Supreme Court seats on the November ballot
B8: Primary source
B9: Washington Public Disclosure Commission (web.pdc.wa.gov). Each candidate's individual committee summary page.
B10: Coverage
B11: 16 declared candidates across Positions 1, 3, 4, 5, and 7. 11 candidates have filed reports; 5 are registered but show 'Not filed' as of the snapshot date.
B13: What 'Raised' means
B14: Cumulative cash contributions reported by the candidate's 2026 election-cycle committee. Excludes in-kind donations unless aggregated by PDC, and excludes independent expenditures made on the candidate's behalf.
B15: What 'Spent' means
... B34: /home/user/workspace/pdc_candidates.txt /home/user/workspace/pdc_schema.json /home/user/workspace/wide/browse_results_mpcy50ce.csv
